README.rst
setup.py
ethjsonrpc/__init__.py
ethjsonrpc/client.py
ethjsonrpc/constants.py
ethjsonrpc/exceptions.py
ethjsonrpc/utils.py
ethjsonrpc.egg-info/PKG-INFO
ethjsonrpc.egg-info/SOURCES.txt
ethjsonrpc.egg-info/dependency_links.txt
ethjsonrpc.egg-info/requires.txt
ethjsonrpc.egg-info/top_level.txt