Metadata-Version: 1.1
Name: ethjsonrpc
Version: 0.2.5
Summary: Ethereum JSON-RPC client
Home-page: https://github.com/ConsenSys/ethjsonrpc
Author: ConsenSys
Author-email: ['info@consensys.net']
License: Unlicense
Platform: UNKNOWN
Classifier: Development Status :: 3 - Alpha
Classifier: Intended Audience :: Developers
Classifier: License :: Public Domain
Classifier: Operating System :: OS Independent
Classifier: Programming Language :: Python
Classifier: Programming Language :: Python :: 2
